jupyter_auth/__init__.py
jupyter_auth/_version.py
jupyter_auth/handlers.py
jupyter_auth/tests/__init__.py
jupyter_auth/tests/test_handlers.py
jupyter_auth-0.0.2.data/data/etc/jupyter/jupyter_notebook_config.d/jupyter_auth.json
jupyter_auth-0.0.2.data/data/etc/jupyter/jupyter_server_config.d/jupyter_auth.json
jupyter_auth-0.0.2.data/data/share/jupyter/labextensions/@datalayer/jupyter-auth/build_log.json
jupyter_auth-0.0.2.data/data/share/jupyter/labextensions/@datalayer/jupyter-auth/package.json
jupyter_auth-0.0.2.data/data/share/jupyter/labextensions/@datalayer/jupyter-auth/schemas/@datalayer/jupyter-admin/package.json.orig
jupyter_auth-0.0.2.data/data/share/jupyter/labextensions/@datalayer/jupyter-auth/schemas/@datalayer/jupyter-admin/plugin.json
jupyter_auth-0.0.2.data/data/share/jupyter/labextensions/@datalayer/jupyter-auth/static/lib_index_js.4348b810ae8dc12e002f.js
jupyter_auth-0.0.2.data/data/share/jupyter/labextensions/@datalayer/jupyter-auth/static/lib_index_js.4348b810ae8dc12e002f.js.map
jupyter_auth-0.0.2.data/data/share/jupyter/labextensions/@datalayer/jupyter-auth/static/remoteEntry.60045aa25abfdbe55e4f.js
jupyter_auth-0.0.2.data/data/share/jupyter/labextensions/@datalayer/jupyter-auth/static/remoteEntry.60045aa25abfdbe55e4f.js.map
jupyter_auth-0.0.2.data/data/share/jupyter/labextensions/@datalayer/jupyter-auth/static/style.js
jupyter_auth-0.0.2.data/data/share/jupyter/labextensions/@datalayer/jupyter-auth/static/style_index_js.09ea6e1de3ce833faf40.js
jupyter_auth-0.0.2.data/data/share/jupyter/labextensions/@datalayer/jupyter-auth/static/style_index_js.09ea6e1de3ce833faf40.js.map
jupyter_auth-0.0.2.data/data/share/jupyter/labextensions/@datalayer/jupyter-auth/static/vendors-node_modules_css-loader_dist_runtime_api_js-node_modules_css-loader_dist_runtime_cssW-72eba1.bac0ab4f283009af8f3d.js
jupyter_auth-0.0.2.dist-info/METADATA
jupyter_auth-0.0.2.dist-info/WHEEL
jupyter_auth-0.0.2.dist-info/licenses/LICENSE
jupyter_auth-0.0.2.dist-info/RECORD
